MANIFEST.in
setup.py
shitman
Shitman.egg-info/PKG-INFO
Shitman.egg-info/SOURCES.txt
Shitman.egg-info/dependency_links.txt
Shitman.egg-info/requires.txt
Shitman.egg-info/top_level.txt
bot/__init__.py
bot/base.py
bot/server.py