Metadata-Version: 1.1
Name: Shitman
Version: 0.1.0
Summary: Yet Another IRC bot
Home-page: https://bitbucket.org/lxsameer/shitman/overview
Author: Sameer Rahmani
Author-email: lxsameer@gnu.org
License: GPL v2
Keywords: IRC bot
Platform: UNKNOWN
Classifier: Development Status :: 5 - Production/Stable
Classifier: Environment :: Console
Classifier: Intended Audience :: Developers
Classifier: License :: OSI Approved :: GNU General Public License (GPL)
Classifier: Operating System :: POSIX :: Linux
Classifier: Programming Language :: Python
Classifier: Topic :: Software Development :: Libraries :: Python Modules
Classifier: Topic :: Utilities
